{
  "request_info": {
    "success": true,
    "credits_used": 5,
    "credits_remaining": 95,
    "credits_used_this_request": 1
  },
  "request_metadata": {
    "created_at": "2022-04-25T14:47:17.168Z",
    "processed_at": "2022-04-25T14:47:20.353Z",
    "total_time_taken": 3.19,
    "amazon_url": "https://www.amazon.com/s/ref=nb_sb_noss?url=node=2975446011"
  },
  "request_parameters": {
    "type": "category",
    "url": "https://www.amazon.com/s/ref=nb_sb_noss?url=node=2975446011",
    "field-keywords": ""
  },
  "category_results": [
    {
      "position": 1,
      "title": "PENN-PLAX Quick-Net Aquarium Fish Nets – Durable, Strong, and Safe – Color May Vary (Blue or Green)",
      "asin": "B0002APXKA",
      "link": "https://www.amazon.com/dp/B0002APXKA",
      "categories": [{ "name": "Fish & Aquatic Pets" }],
      "image": "https://m.media-amazon.com/images/I/51cyYrpUqYL._AC_UL320_.jpg",
      "is_prime": false,
      "rating": 4.7,
      "ratings_total": 13910,
      "sponsored": false
    },
    {
      "position": 2,
      "title": "API STRESS COAT Aquarium Water Conditioner 16-Ounce Bottle",
      "asin": "B000255MZG",
      "link": "https://www.amazon.com/dp/B000255MZG",
      "categories": [{ "name": "Fish & Aquatic Pets" }],
      "image": "https://m.media-amazon.com/images/I/713Ne2JzZ0L._AC_UL320_.jpg",
      "is_prime": false,
      "rating": 4.8,
      "ratings_total": 16786,
      "sponsored": false
    },
    {
      "position": 3,
      "title": "Marineland Rite-Size Cartridge C, 6-Pack",
      "asin": "B000256EKS",
      "link": "https://www.amazon.com/dp/B000256EKS",
      "categories": [{ "name": "Fish & Aquatic Pets" }],
      "image": "https://m.media-amazon.com/images/I/91bq0m8rS1L._AC_UL320_.jpg",
      "is_prime": false,
      "rating": 4.7,
      "ratings_total": 21649,
      "sponsored": false
    },
    {
      "position": 4,
      "title": "Tetra Whisper Bio-Bag Disposable Filter Cartridges 3 Count, For aquariums, Medium (26169)",
      "asin": "B0006JM09E",
      "link": "https://www.amazon.com/dp/B0006JM09E",
      "categories": [{ "name": "Fish & Aquatic Pets" }],
      "image": "https://m.media-amazon.com/images/I/61u0h3kolhL._AC_UL320_.jpg",
      "is_prime": false,
      "rating": 4.7,
      "ratings_total": 22311,
      "sponsored": false
    },
    {
      "position": 5,
      "title": "PENN-PLAX Standard Airline Tubing for Aquariums – Clear and Flexible – Resists Kinking – Safe for Freshwater and Saltwater Fish Tanks – 8 Feet",
      "asin": "B0002563MM",
      "link": "https://www.amazon.com/dp/B0002563MM",
      "categories": [{ "name": "Fish & Aquatic Pets" }],
      "image": "https://m.media-amazon.com/images/I/61IzoEFjSuL._AC_UL320_.jpg",
      "is_prime": false,
      "rating": 4.6,
      "ratings_total": 12533,
      "sponsored": false
    },
    {
      "position": 6,
      "title": "VIVOSUN 800GPH Submersible Pump(3000L/H, 24W), Ultra Quiet Water Pump with 10ft. High Lift, Fountain Pump with 6.5ft. Power Cord, 3 Nozzles for Fish Tank, Pond, Aquarium, Statuary, Hydroponics",
      "asin": "B07L54HB83",
      "link": "https://www.amazon.com/dp/B07L54HB83",
      "categories": [{ "name": "Fish & Aquatic Pets" }],
      "image": "https://m.media-amazon.com/images/I/718WM7imi0L._AC_UL320_.jpg",
      "is_prime": false,
      "rating": 4.5,
      "ratings_total": 16268,
      "sponsored": false,
      "prices": [
        {
          "symbol": "$",
          "value": 24.99,
          "currency": "USD",
          "raw": "$24.99",
          "name": "primary"
        },
        {
          "symbol": "$",
          "value": 26.99,
          "currency": "USD",
          "raw": "$26.99",
          "name": "original"
        }
      ],
      "price": {
        "symbol": "$",
        "value": 24.99,
        "currency": "USD",
        "raw": "$24.99",
        "name": "primary"
      }
    },
    {
      "position": 7,
      "title": "Tetra Whisper Easy to Use Air Pump for Aquariums (Non-UL)",
      "asin": "B0009YJ4N6",
      "link": "https://www.amazon.com/dp/B0009YJ4N6",
      "categories": [{ "name": "Fish & Aquatic Pets" }],
      "image": "https://m.media-amazon.com/images/I/91afSvADX0L._AC_UL320_.jpg",
      "is_prime": false,
      "rating": 4.6,
      "ratings_total": 30066,
      "sponsored": false
    },
    {
      "position": 8,
      "title": "API TAP WATER CONDITIONER Aquarium Water Conditioner 16-Ounce Bottle, White (52C)",
      "asin": "B004LO9KSY",
      "link": "https://www.amazon.com/dp/B004LO9KSY",
      "categories": [{ "name": "Fish & Aquatic Pets" }],
      "image": "https://m.media-amazon.com/images/I/71dMPkd8H-L._AC_UL320_.jpg",
      "is_prime": false,
      "rating": 4.7,
      "ratings_total": 15545,
      "sponsored": false
    },
    {
      "position": 9,
      "title": "API FRESHWATER MASTER TEST KIT 800-Test Freshwater Aquarium Water Master Test Kit, White, Single, Multi-colored",
      "asin": "B000255NCI",
      "link": "https://www.amazon.com/dp/B000255NCI",
      "categories": [{ "name": "Fish & Aquatic Pets" }],
      "image": "https://m.media-amazon.com/images/I/81OQUKG2l9L._AC_UL320_.jpg",
      "is_prime": false,
      "rating": 4.7,
      "ratings_total": 22714,
      "sponsored": false
    },
    {
      "position": 10,
      "title": "Seachem Prime Fresh and Saltwater Conditioner - Chemical Remover and Detoxifier 500 ml",
      "asin": "B00025694O",
      "link": "https://www.amazon.com/dp/B00025694O",
      "categories": [{ "name": "Fish & Aquatic Pets" }],
      "image": "https://m.media-amazon.com/images/I/513AEZMdFHL._AC_UL320_.jpg",
      "is_prime": false,
      "rating": 4.8,
      "ratings_total": 26241,
      "sponsored": false
    },
    {
      "position": 11,
      "title": "Tetra PRO PlecoWafers 5.29 Ounces, Nutritionally Balanced Vegetarian Fish Food, Concentrated Algae Center",
      "asin": "B0017JAPMQ",
      "link": "https://www.amazon.com/dp/B0017JAPMQ",
      "categories": [{ "name": "Fish & Aquatic Pets" }],
      "image": "https://m.media-amazon.com/images/I/71t5OxkpANS._AC_UL320_.jpg",
      "is_prime": false,
      "rating": 4.6,
      "ratings_total": 13586,
      "sponsored": false
    },
    {
      "position": 12,
      "title": "Tetra 77080 Pro Tropical Color Crisps, Fish Food With Natural Color Enhancers,7.41-Ounce (210 g)",
      "asin": "B00JN9I7F4",
      "link": "https://www.amazon.com/dp/B00JN9I7F4",
      "categories": [{ "name": "Fish & Aquatic Pets" }],
      "image": "https://m.media-amazon.com/images/I/91hk1zvMGCL._AC_UL320_.jpg",
      "is_prime": false,
      "rating": 4.7,
      "ratings_total": 4751,
      "sponsored": false
    }
  ],
  "category_information": { "is_landing_page": true },
  "refinements": {
    "department": [
      {
        "name": "Pet Supplies",
        "link": "https://www.amazon.com/Pet-Supplies/b?ie=UTF8&node=2619533011",
        "refinement_display_name": "Department"
      },
      {
        "name": "Aquarium Cleaners",
        "link": "https://www.amazon.com/Aquarium-Cleaners-Fish-Aquatic-Pets/b?ie=UTF8&node=2975464011",
        "refinement_display_name": "Department"
      },
      {
        "name": "Aquarium Décor",
        "link": "https://www.amazon.com/Aquarium-D%C3%A9cor-Fish-Aquatic-Pets/b?ie=UTF8&node=2975448011",
        "refinement_display_name": "Department"
      },
      {
        "name": "Aquarium Heaters & Chillers",
        "link": "https://www.amazon.com/Aquarium-Heaters-Chillers-Fish-Aquatic-Pets/b?ie=UTF8&node=19171761011",
        "refinement_display_name": "Department"
      },
      {
        "name": "Aquarium Hoods",
        "link": "https://www.amazon.com/Aquarium-Hoods-Fish-Aquatic-Pets/b?ie=UTF8&node=2975457011",
        "refinement_display_name": "Department"
      },
      {
        "name": "Aquarium Hydrometers",
        "link": "https://www.amazon.com/Aquarium-Hydrometers-Fish-Aquatic-Pets/b?ie=UTF8&node=3048857011",
        "refinement_display_name": "Department"
      },
      {
        "name": "Aquarium Lights",
        "link": "https://www.amazon.com/Aquarium-Lights-Fish-Aquatic-Pets/b?ie=UTF8&node=2975458011",
        "refinement_display_name": "Department"
      },
      {
        "name": "Aquarium Pumps & Filters",
        "link": "https://www.amazon.com/Aquarium-Pumps-Filters-Fish-Aquatic-Pets/b?ie=UTF8&node=2975469011",
        "refinement_display_name": "Department"
      },
      {
        "name": "Aquarium Stands",
        "link": "https://www.amazon.com/Aquarium-Stands-Fish-Aquatic-Pets/b?ie=UTF8&node=2975459011",
        "refinement_display_name": "Department"
      },
      {
        "name": "Aquarium Substrate",
        "link": "https://www.amazon.com/Aquarium-Substrate-Fish-Aquatic-Pets/b?ie=UTF8&node=2975476011",
        "refinement_display_name": "Department"
      },
      {
        "name": "Aquarium Test Kits",
        "link": "https://www.amazon.com/Aquarium-Test-Kits-Fish-Aquatic-Pets/b?ie=UTF8&node=3048858011",
        "refinement_display_name": "Department"
      },
      {
        "name": "Aquarium Thermometers",
        "link": "https://www.amazon.com/Aquarium-Thermometers-Fish-Aquatic-Pets/b?ie=UTF8&node=2975477011",
        "refinement_display_name": "Department"
      },
      {
        "name": "Aquarium Water Treatments",
        "link": "https://www.amazon.com/Aquarium-Water-Treatments-Fish-Aquatic-Pets/b?ie=UTF8&node=2975478011",
        "refinement_display_name": "Department"
      },
      {
        "name": "Aquariums & Fish Bowls",
        "link": "https://www.amazon.com/Aquariums-Fish-Bowls-Aquatic-Pets/b?ie=UTF8&node=7955292011",
        "refinement_display_name": "Department"
      },
      {
        "name": "Automatic Feeders",
        "link": "https://www.amazon.com/Automatic-Feeders-Fish-Aquatic-Pets/b?ie=UTF8&node=2975462011",
        "refinement_display_name": "Department"
      },
      {
        "name": "Breeding Tanks",
        "link": "https://www.amazon.com/Breeding-Tanks-Fish-Aquatic-Pets/b?ie=UTF8&node=2975463011",
        "refinement_display_name": "Department"
      },
      {
        "name": "Food",
        "link": "https://www.amazon.com/Food-Fish-Aquatic-Pets/b?ie=UTF8&node=2975479011",
        "refinement_display_name": "Department"
      },
      {
        "name": "Medication & Health Supplies",
        "link": "https://www.amazon.com/Medication-Health-Supplies-Fish-Aquatic-Pets/b?ie=UTF8&node=21238281011",
        "refinement_display_name": "Department"
      }
    ],
    "climate_pledge_friendly": [
      {
        "name": "Climate Pledge Friendly",
        "link": "https://www.amazon.com/Fish-Aquatic-Pets-Climate-Pledge-Friendly/s?rh=n%3A2975446011%2Cp_n_cpf_eligible%3A21512497011",
        "refinement_display_name": "Climate Pledge Friendly"
      }
    ],
    "subscribe_and_save": [
      {
        "name": "Subscribe & Save Eligible",
        "link": "https://www.amazon.com/Fish-Aquatic-Pets-Subscribe-Save-Eligible/s?rh=n%3A2975446011%2Cp_n_is_sns_available%3A2617006011",
        "refinement_display_name": "Subscribe & Save"
      }
    ],
    "eligible_for_free_shipping": [
      {
        "name": "Free Shipping by Amazon\n\n    \n    \n        \n            \n                \n\nAll customers get FREE Shipping on orders over $25 shipped by Amazon",
        "link": "https://www.amazon.com/Fish-Aquatic-Pets-Free-Shipping-Amazon/s?rh=n%3A2975446011%2Cp_76%3A2661625011",
        "refinement_display_name": "Eligible for Free Shipping"
      }
    ],
    "from_our_brands": [
      {
        "name": "Our Brands",
        "link": "https://www.amazon.com/Fish-Aquatic-Pets-Our-Brands/s?rh=n%3A2975446011%2Cp_n_feature_forty-seven_browse-bin%3A21180942011",
        "refinement_display_name": "From Our Brands"
      }
    ],
    "featured_brands": [
      {
        "name": "Penn-Plax",
        "link": "https://www.amazon.com/Fish-Aquatic-Pets-Penn-Plax-Pet-Supplies/s?rh=n%3A2975446011%2Cp_89%3APenn-Plax",
        "refinement_display_name": "Featured Brands"
      },
      {
        "name": "API",
        "link": "https://www.amazon.com/Fish-Aquatic-Pets-API-Pet-Supplies/s?rh=n%3A2975446011%2Cp_89%3AAPI",
        "refinement_display_name": "Featured Brands"
      },
      {
        "name": "MarineLand",
        "link": "https://www.amazon.com/Fish-Aquatic-Pets-MarineLand-Pet-Supplies/s?rh=n%3A2975446011%2Cp_89%3AMarineLand",
        "refinement_display_name": "Featured Brands"
      },
      {
        "name": "Tetra",
        "link": "https://www.amazon.com/Fish-Aquatic-Pets-Tetra-Pet-Supplies/s?rh=n%3A2975446011%2Cp_89%3ATetra",
        "refinement_display_name": "Featured Brands"
      },
      {
        "name": "VIVOSUN",
        "link": "https://www.amazon.com/Fish-Aquatic-Pets-VIVOSUN-Pet-Supplies/s?rh=n%3A2975446011%2Cp_89%3AVIVOSUN",
        "refinement_display_name": "Featured Brands"
      },
      {
        "name": "Seachem",
        "link": "https://www.amazon.com/Fish-Aquatic-Pets-Seachem-Pet-Supplies/s?rh=n%3A2975446011%2Cp_89%3ASeachem",
        "refinement_display_name": "Featured Brands"
      },
      {
        "name": "Aqueon",
        "link": "https://www.amazon.com/Fish-Aquatic-Pets-Aqueon-Pet-Supplies/s?rh=n%3A2975446011%2Cp_89%3AAqueon",
        "refinement_display_name": "Featured Brands"
      }
    ],
    "packaging_option": [
      {
        "name": "Frustration-Free Packaging",
        "link": "https://www.amazon.com/Fish-Aquatic-Pets-Frustration-Free-Packaging/s?rh=n%3A2975446011%2Cp_n_is_ffp%3A7252855011",
        "refinement_display_name": "Packaging Option"
      }
    ],
    "avg_customer_review": [
      {
        "name": "4 Stars & Up\n    \n\n\n        \n            \n\n& Up",
        "link": "https://www.amazon.com/Fish-Aquatic-Pets-4-Stars-Up/s?rh=n%3A2975446011%2Cp_72%3A2661618011",
        "refinement_display_name": "Avg. Customer Review"
      },
      {
        "name": "3 Stars & Up\n    \n\n\n        \n            \n\n& Up",
        "link": "https://www.amazon.com/Fish-Aquatic-Pets-3-Stars-Up/s?rh=n%3A2975446011%2Cp_72%3A2661619011",
        "refinement_display_name": "Avg. Customer Review"
      },
      {
        "name": "2 Stars & Up\n    \n\n\n        \n            \n\n& Up",
        "link": "https://www.amazon.com/Fish-Aquatic-Pets-2-Stars-Up/s?rh=n%3A2975446011%2Cp_72%3A2661620011",
        "refinement_display_name": "Avg. Customer Review"
      },
      {
        "name": "1 Star & Up\n    \n\n\n        \n            \n\n& Up",
        "link": "https://www.amazon.com/Fish-Aquatic-Pets-1-Star-Up/s?rh=n%3A2975446011%2Cp_72%3A2661621011",
        "refinement_display_name": "Avg. Customer Review"
      }
    ],
    "new_arrivals": [
      {
        "name": "Last 30 days",
        "link": "https://www.amazon.com/Fish-Aquatic-Pets-Last-30-days/s?rh=n%3A2975446011%2Cp_n_date_first_available_absolute%3A2661609011",
        "refinement_display_name": "New Arrivals"
      },
      {
        "name": "Last 90 days",
        "link": "https://www.amazon.com/Fish-Aquatic-Pets-Last-90-days/s?rh=n%3A2975446011%2Cp_n_date_first_available_absolute%3A2661610011",
        "refinement_display_name": "New Arrivals"
      }
    ],
    "international_shipping": [
      {
        "name": "International Shipping Eligible",
        "link": "https://www.amazon.com/Fish-Aquatic-Pets-International-Shipping-Eligible/s?rh=n%3A2975446011%2Cp_n_shipping_option-bin%3A3242350011",
        "refinement_display_name": "International Shipping"
      }
    ],
    "price": [
      {
        "name": "Up to $25",
        "link": "https://www.amazon.com/Fish-Aquatic-Pets-Up-25/s?rh=n%3A2975446011%2Cp_36%3A2661612011",
        "refinement_display_name": "Price"
      },
      {
        "name": "$25 to $50",
        "link": "https://www.amazon.com/Fish-Aquatic-Pets-25-50/s?rh=n%3A2975446011%2Cp_36%3A2661613011",
        "refinement_display_name": "Price"
      },
      {
        "name": "$50 to $100",
        "link": "https://www.amazon.com/Fish-Aquatic-Pets-50-100/s?rh=n%3A2975446011%2Cp_36%3A2661614011",
        "refinement_display_name": "Price"
      },
      {
        "name": "$100 to $200",
        "link": "https://www.amazon.com/Fish-Aquatic-Pets-100-200/s?rh=n%3A2975446011%2Cp_36%3A2661615011",
        "refinement_display_name": "Price"
      },
      {
        "name": "$200 & above",
        "link": "https://www.amazon.com/Fish-Aquatic-Pets-200-above/s?rh=n%3A2975446011%2Cp_36%3A2661616011",
        "refinement_display_name": "Price"
      }
    ],
    "deals": [
      {
        "name": "Today's Deals",
        "link": "https://www.amazon.com/Fish-Aquatic-Pets-Todays-Deals/s?rh=n%3A2975446011%2Cp_n_specials_match%3A21213697011",
        "refinement_display_name": "Deals"
      }
    ],
    "seller": [
      {
        "name": "Amazon.com",
        "link": "https://www.amazon.com/Fish-Aquatic-Pets-Amazon-com/s?rh=n%3A2975446011%2Cp_6%3AATVPDKIKX0DER",
        "refinement_display_name": "Seller"
      },
      {
        "name": "SGHP",
        "link": "https://www.amazon.com/Fish-Aquatic-Pets-SGHP-Pet-Supplies/s?rh=n%3A2975446011%2Cp_6%3AA3VZKFNMHAPZBO",
        "refinement_display_name": "Seller"
      },
      {
        "name": "my Goods",
        "link": "https://www.amazon.com/Fish-Aquatic-Pets-my-Goods/s?rh=n%3A2975446011%2Cp_6%3AA2CK5NG72UVSTT",
        "refinement_display_name": "Seller"
      },
      {
        "name": "MarineAndReef",
        "link": "https://www.amazon.com/Fish-Aquatic-Pets-MarineAndReef-Pet-Supplies/s?rh=n%3A2975446011%2Cp_6%3AA1ZIOKDYA2KMI2",
        "refinement_display_name": "Seller"
      },
      {
        "name": "Amazon Export Sales LLC",
        "link": "https://www.amazon.com/Fish-Aquatic-Pets-Pet-Supplies/s?rh=n%3A2975446011%2Cp_6%3AA2XZ7JICGUQ1CX",
        "refinement_display_name": "Seller"
      },
      {
        "name": "Petco",
        "link": "https://www.amazon.com/Fish-Aquatic-Pets-Petco-Pet-Supplies/s?rh=n%3A2975446011%2Cp_6%3AA2LDZGFAGG1QXE",
        "refinement_display_name": "Seller"
      },
      {
        "name": "bluemed",
        "link": "https://www.amazon.com/Fish-Aquatic-Pets-bluemed-Pet-Supplies/s?rh=n%3A2975446011%2Cp_6%3AAKGQ69TTJ5VEW",
        "refinement_display_name": "Seller"
      },
      {
        "name": "Deal4K",
        "link": "https://www.amazon.com/Fish-Aquatic-Pets-Deal4K-Pet-Supplies/s?rh=n%3A2975446011%2Cp_6%3AA2NN6T5HOWCIUK",
        "refinement_display_name": "Seller"
      },
      {
        "name": "Kens Fish",
        "link": "https://www.amazon.com/Fish-Aquatic-Pets-Kens-Pet-Supplies/s?rh=n%3A2975446011%2Cp_6%3AA2GY0XK4NUNEG1",
        "refinement_display_name": "Seller"
      },
      {
        "name": "AlotOfHome",
        "link": "https://www.amazon.com/Fish-Aquatic-Pets-AlotOfHome-Pet-Supplies/s?rh=n%3A2975446011%2Cp_6%3AA2Z97RC3GHC1Y",
        "refinement_display_name": "Seller"
      }
    ],
    "availability": [
      {
        "name": "Include Out of Stock",
        "link": "https://www.amazon.com/Fish-Aquatic-Pets-Include-Out-Stock/s?rh=n%3A2975446011%2Cp_n_availability%3A2661601011",
        "refinement_display_name": "Availability"
      }
    ]
  },
  "category_list": [
    {
      "title": "Aquarium Décor",
      "link": "https://www.amazon.com/b/?node=2975448011&ref_=Oct_d_odnav_d_2975446011_0&pd_rd_w=Lvzs5&pf_rd_p=72459b27-e231-4837-b61c-b057ff0c50ac&pf_rd_r=RG5BESKY0BTWAHZ8DXMW&pd_rd_r=d60d775c-aa3d-4363-b500-de9ef7e5c006&pd_rd_wg=k2rrq",
      "image": "https://images-na.ssl-images-amazon.com/images/I/41KEX5L+jUL._AC._SR120,120.jpg"
    },
    {
      "title": "Aquarium Pumps & Filters",
      "link": "https://www.amazon.com/b/?node=2975469011&ref_=Oct_d_odnav_d_2975446011_1&pd_rd_w=Lvzs5&pf_rd_p=72459b27-e231-4837-b61c-b057ff0c50ac&pf_rd_r=RG5BESKY0BTWAHZ8DXMW&pd_rd_r=d60d775c-aa3d-4363-b500-de9ef7e5c006&pd_rd_wg=k2rrq",
      "image": "https://images-na.ssl-images-amazon.com/images/I/51pzTEeMoXL._AC._SR120,120.jpg"
    },
    {
      "title": "Food",
      "link": "https://www.amazon.com/b/?node=2975479011&ref_=Oct_d_odnav_d_2975446011_2&pd_rd_w=Lvzs5&pf_rd_p=72459b27-e231-4837-b61c-b057ff0c50ac&pf_rd_r=RG5BESKY0BTWAHZ8DXMW&pd_rd_r=d60d775c-aa3d-4363-b500-de9ef7e5c006&pd_rd_wg=k2rrq",
      "image": "https://images-na.ssl-images-amazon.com/images/I/51KFHJXNMIL._AC._SR120,120.jpg"
    },
    {
      "title": "Aquarium Water Treatments",
      "link": "https://www.amazon.com/b/?node=2975478011&ref_=Oct_d_odnav_d_2975446011_3&pd_rd_w=Lvzs5&pf_rd_p=72459b27-e231-4837-b61c-b057ff0c50ac&pf_rd_r=RG5BESKY0BTWAHZ8DXMW&pd_rd_r=d60d775c-aa3d-4363-b500-de9ef7e5c006&pd_rd_wg=k2rrq",
      "image": "https://images-na.ssl-images-amazon.com/images/I/41S6GrCbf3L._AC._SR120,120.jpg"
    },
    {
      "title": "Aquarium Lights",
      "link": "https://www.amazon.com/b/?node=2975458011&ref_=Oct_d_odnav_d_2975446011_4&pd_rd_w=Lvzs5&pf_rd_p=72459b27-e231-4837-b61c-b057ff0c50ac&pf_rd_r=RG5BESKY0BTWAHZ8DXMW&pd_rd_r=d60d775c-aa3d-4363-b500-de9ef7e5c006&pd_rd_wg=k2rrq",
      "image": "https://images-na.ssl-images-amazon.com/images/I/41B8Lwipm8L._AC._SR120,120.jpg"
    },
    {
      "title": "Aquariums & Fish Bowls",
      "link": "https://www.amazon.com/b/?node=7955292011&ref_=Oct_d_odnav_d_2975446011_5&pd_rd_w=Lvzs5&pf_rd_p=72459b27-e231-4837-b61c-b057ff0c50ac&pf_rd_r=RG5BESKY0BTWAHZ8DXMW&pd_rd_r=d60d775c-aa3d-4363-b500-de9ef7e5c006&pd_rd_wg=k2rrq",
      "image": "https://images-na.ssl-images-amazon.com/images/I/41dfaPjI9-L._AC._SR120,120.jpg"
    },
    {
      "title": "Aquarium Cleaners",
      "link": "https://www.amazon.com/b/?node=2975464011&ref_=Oct_d_odnav_d_2975446011_6&pd_rd_w=Lvzs5&pf_rd_p=72459b27-e231-4837-b61c-b057ff0c50ac&pf_rd_r=RG5BESKY0BTWAHZ8DXMW&pd_rd_r=d60d775c-aa3d-4363-b500-de9ef7e5c006&pd_rd_wg=k2rrq",
      "image": "https://images-na.ssl-images-amazon.com/images/I/317t-qrwHXL._AC._SR120,120.jpg"
    },
    {
      "title": "Aquarium Substrate",
      "link": "https://www.amazon.com/b/?node=2975476011&ref_=Oct_d_odnav_d_2975446011_7&pd_rd_w=Lvzs5&pf_rd_p=72459b27-e231-4837-b61c-b057ff0c50ac&pf_rd_r=RG5BESKY0BTWAHZ8DXMW&pd_rd_r=d60d775c-aa3d-4363-b500-de9ef7e5c006&pd_rd_wg=k2rrq",
      "image": "https://images-na.ssl-images-amazon.com/images/I/413pniC0m8L._AC._SR120,120.jpg"
    },
    {
      "title": "Aquarium Hydrometers",
      "link": "https://www.amazon.com/b/?node=3048857011&ref_=Oct_d_odnav_d_2975446011_8&pd_rd_w=Lvzs5&pf_rd_p=72459b27-e231-4837-b61c-b057ff0c50ac&pf_rd_r=RG5BESKY0BTWAHZ8DXMW&pd_rd_r=d60d775c-aa3d-4363-b500-de9ef7e5c006&pd_rd_wg=k2rrq",
      "image": "https://images-na.ssl-images-amazon.com/images/I/41l3Wk2lLwL._AC._SR120,120.jpg"
    },
    {
      "title": "Aquarium Heaters & Chillers",
      "link": "https://www.amazon.com/b/?_encoding=UTF8&node=19171761011&bbn=2619533011&ref_=Oct_d_odnav_d_2975446011_9&pd_rd_w=Lvzs5&pf_rd_p=72459b27-e231-4837-b61c-b057ff0c50ac&pf_rd_r=RG5BESKY0BTWAHZ8DXMW&pd_rd_r=d60d775c-aa3d-4363-b500-de9ef7e5c006&pd_rd_wg=k2rrq",
      "image": "https://images-na.ssl-images-amazon.com/images/I/41jrM9d6VdL._AC._SR120,120.jpg"
    },
    {
      "title": "Aquarium Hoods",
      "link": "https://www.amazon.com/b/?node=2975457011&ref_=Oct_d_odnav_d_2975446011_10&pd_rd_w=Lvzs5&pf_rd_p=72459b27-e231-4837-b61c-b057ff0c50ac&pf_rd_r=RG5BESKY0BTWAHZ8DXMW&pd_rd_r=d60d775c-aa3d-4363-b500-de9ef7e5c006&pd_rd_wg=k2rrq",
      "image": "https://images-na.ssl-images-amazon.com/images/I/312kVp5O05L._AC._SR120,120.jpg"
    },
    {
      "title": "Aquarium Test Kits",
      "link": "https://www.amazon.com/b/?node=3048858011&ref_=Oct_d_odnav_d_2975446011_11&pd_rd_w=Lvzs5&pf_rd_p=72459b27-e231-4837-b61c-b057ff0c50ac&pf_rd_r=RG5BESKY0BTWAHZ8DXMW&pd_rd_r=d60d775c-aa3d-4363-b500-de9ef7e5c006&pd_rd_wg=k2rrq",
      "image": "https://images-na.ssl-images-amazon.com/images/I/51hc0BPGWQL._AC._SR120,120.jpg"
    },
    {
      "title": "Aquarium Stands",
      "link": "https://www.amazon.com/b/?node=2975459011&ref_=Oct_d_odnav_d_2975446011_12&pd_rd_w=Lvzs5&pf_rd_p=72459b27-e231-4837-b61c-b057ff0c50ac&pf_rd_r=RG5BESKY0BTWAHZ8DXMW&pd_rd_r=d60d775c-aa3d-4363-b500-de9ef7e5c006&pd_rd_wg=k2rrq",
      "image": "https://images-na.ssl-images-amazon.com/images/I/41fX6oQTiPL._AC._SR120,120.jpg"
    },
    {
      "title": "Breeding Tanks",
      "link": "https://www.amazon.com/b/?node=2975463011&ref_=Oct_d_odnav_d_2975446011_13&pd_rd_w=Lvzs5&pf_rd_p=72459b27-e231-4837-b61c-b057ff0c50ac&pf_rd_r=RG5BESKY0BTWAHZ8DXMW&pd_rd_r=d60d775c-aa3d-4363-b500-de9ef7e5c006&pd_rd_wg=k2rrq",
      "image": "https://images-na.ssl-images-amazon.com/images/I/51XNutLNypL._AC._SR120,120.jpg"
    },
    {
      "title": "Automatic Feeders",
      "link": "https://www.amazon.com/b/?node=2975462011&ref_=Oct_d_odnav_d_2975446011_14&pd_rd_w=Lvzs5&pf_rd_p=72459b27-e231-4837-b61c-b057ff0c50ac&pf_rd_r=RG5BESKY0BTWAHZ8DXMW&pd_rd_r=d60d775c-aa3d-4363-b500-de9ef7e5c006&pd_rd_wg=k2rrq",
      "image": "https://images-na.ssl-images-amazon.com/images/I/41Mlc-3jtqS._AC._SR120,120.jpg"
    },
    {
      "title": "Aquarium Thermometers",
      "link": "https://www.amazon.com/b/?node=2975477011&ref_=Oct_d_odnav_d_2975446011_15&pd_rd_w=Lvzs5&pf_rd_p=72459b27-e231-4837-b61c-b057ff0c50ac&pf_rd_r=RG5BESKY0BTWAHZ8DXMW&pd_rd_r=d60d775c-aa3d-4363-b500-de9ef7e5c006&pd_rd_wg=k2rrq",
      "image": "https://images-na.ssl-images-amazon.com/images/I/41L8EmsV7RL._AC._SR120,120.jpg"
    },
    {
      "title": "Medication & Health Supplies",
      "link": "https://www.amazon.com/b/?_encoding=UTF8&node=21238281011&bbn=2619533011&ref_=Oct_d_odnav_d_2975446011_16&pd_rd_w=Lvzs5&pf_rd_p=72459b27-e231-4837-b61c-b057ff0c50ac&pf_rd_r=RG5BESKY0BTWAHZ8DXMW&pd_rd_r=d60d775c-aa3d-4363-b500-de9ef7e5c006&pd_rd_wg=k2rrq",
      "image": "https://images-na.ssl-images-amazon.com/images/I/518W2jyjhAL._AC._SR120,120.jpg"
    }
  ],
  "pagination": { "total_results": 20000 }
}
